{
  "url": "https://www.mzsa.ru/goods/water/water_34.html",
  "title": "Прицеп для академических судов",
  "model": "МЗСА V",
  "version": "102",
  "description": "Надёжное\n\nV-образное\n\nдышло\n\nвыдерживает сильные динамические нагрузки и оснащено\n\nкронштейном крепления запасного колеса\n\n.\n\nПлатформа прицепа оборудована отсеком для перевозки оборудования и инвентаря.\n\nПередвижной колесный ход\n\nпозволяет правильно распределить центр тяжести перевозимого груза.\n\nЛожементы\n\nпозволяют равномерно распределить вес судна и уменьшить давление на его корпус.\n\nВыдвижной фартук с габаритными фонарями\n\nнеобходим при перевозке техники выступающей за пределы прицепа более чем на 1 метр.\n\nОпорное колесо\n\nобеспечивает горизонтальное положение прицепа и облегчает его перемещение без тягача.\n\nТри автономные тормозные системы: Рабочая тормозная система\n\n— для служебного и экстренного торможения в составе автопоезда.\n\nСтояночная тормозная система\n\n— для фиксации прицепа во время стоянки.\n\nАварийная тормозная система\n\n— для аварийного торможения прицепа при нарушении сцепки с тягачом.\n\nАнтикоррозийное покрытие методом горячего цинкования\n\n, создаёт надежную защиту от коррозии, обеспечивает долговечность прицепа и служит гарантией сохранности всех металлических элементов конструкции.\n\nВ базовую комплектацию входят\n\nпротивооткатные упоры (2 шт.) и запасное колесо R14C (1 шт.)\n\n.\n\nВсе модели сертифицированы. Предоставляется полный комплект документов для постановки на учёт ГИБДД.",
  "specs": {
    "polnaya_massa": 2000,
    "polnaya_massa_unit": "кг",
    "gruzopodemnost": 1100,
    "gruzopodemnost_unit": "кг",
    "gabaritnye_razmery": "8150x2300x2650 мм",
    "gabaritnye_razmery_length": 8150,
    "gabaritnye_razmery_width": 2300,
    "gabaritnye_razmery_height": 2650,
    "dlina_sudna": "8000 мм",
    "podveska": "резино-жгутовая",
    "kol_vo_osey_kolyos": "2/4",
    "dorozhnyy_prosvet": "230 мм",
    "razmer_kolyos": "R14С",
    "tormoz": "тормоз наката"
  },
  "options": [],
  "category": "lodochniy",
  "slug": "mzsa_v_102",
  "scraped_at": "2025-11-22T07:08:39Z",
  "images": [
    "pricep/pritsep_lodka_mzsa_v_102_8m.jpg",
    "pricep/pritsep_lodka_mzsa_v_102_8m_1.jpg",
    "pricep/pritsep_lodka_mzsa_v_102_8m_2.jpg",
    "pricep/pritsep_lodka_mzsa_v_102_8m_3.jpg"
  ]
}